README.rst
setup.py
datacoco_ftp_tools/__init__.py
datacoco_ftp_tools/__version__.py
datacoco_ftp_tools/ftp_tools.py
datacoco_ftp_tools.egg-info/PKG-INFO
datacoco_ftp_tools.egg-info/SOURCES.txt
datacoco_ftp_tools.egg-info/dependency_links.txt
datacoco_ftp_tools.egg-info/requires.txt
datacoco_ftp_tools.egg-info/top_level.txt