Metadata-Version: 1.1
Name: datacoco-ftp-tools
Version: 0.1.3
Summary: Data common code for ftp tools by Equinox
Home-page: https://github.com/equinoxfitness/datacoco-ftp_tools
Author: Equinox Fitness
Author-email: paul.singman@equinox.com
License: MIT
Platform: UNKNOWN
Classifier: Development Status :: 5 - Production/Stable
Classifier: Intended Audience :: Developers
Classifier: Natural Language :: English
Classifier: License :: OSI Approved :: MIT License
Classifier: Programming Language :: Python :: 3.6
